MANIFEST.in
setup.py
LServer/__init__.py
LServer/api.py
LServer/cmd.py
LServer/llocal.py
LServer/lserver.py
LServer/settings.py
LServer/utils.py
LServer/Editor/ckeditor.js
LServer/Editor/editor.html
LServer/Editor/static/bootstrap/dist/css/bootstrap-theme.css
LServer/Editor/static/bootstrap/dist/css/bootstrap-theme.css.map
LServer/Editor/static/bootstrap/dist/css/bootstrap-theme.min.css
LServer/Editor/static/bootstrap/dist/css/bootstrap.css
LServer/Editor/static/bootstrap/dist/css/bootstrap.css.map
LServer/Editor/static/bootstrap/dist/css/bootstrap.min.css
LServer/Editor/static/bootstrap/dist/js/bootstrap.js
LServer/Editor/static/bootstrap/dist/js/bootstrap.min.js
LServer/Editor/static/bootstrap/grunt/bs-glyphicons-data-generator.js
LServer/Editor/static/bootstrap/grunt/bs-lessdoc-parser.js
LServer/Editor/static/bootstrap/grunt/bs-raw-files-generator.js
LServer/Editor/static/bootstrap/grunt/sauce_browsers.yml
LServer/Editor/static/bootstrap/js/affix.js
LServer/Editor/static/bootstrap/js/alert.js
LServer/Editor/static/bootstrap/js/button.js
LServer/Editor/static/bootstrap/js/carousel.js
LServer/Editor/static/bootstrap/js/collapse.js
LServer/Editor/static/bootstrap/js/dropdown.js
LServer/Editor/static/bootstrap/js/modal.js
LServer/Editor/static/bootstrap/js/popover.js
LServer/Editor/static/bootstrap/js/scrollspy.js
LServer/Editor/static/bootstrap/js/tab.js
LServer/Editor/static/bootstrap/js/tooltip.js
LServer/Editor/static/bootstrap/js/transition.js
LServer/Editor/static/bootstrap/less/alerts.less
LServer/Editor/static/bootstrap/less/badges.less
LServer/Editor/static/bootstrap/less/bootstrap.less
LServer/Editor/static/bootstrap/less/breadcrumbs.less
LServer/Editor/static/bootstrap/less/button-groups.less
LServer/Editor/static/bootstrap/less/buttons.less
LServer/Editor/static/bootstrap/less/carousel.less
LServer/Editor/static/bootstrap/less/close.less
LServer/Editor/static/bootstrap/less/code.less
LServer/Editor/static/bootstrap/less/component-animations.less
x_mroy_1048.egg-info/PKG-INFO
x_mroy_1048.egg-info/SOURCES.txt
x_mroy_1048.egg-info/dependency_links.txt
x_mroy_1048.egg-info/entry_points.txt
x_mroy_1048.egg-info/not-zip-safe
x_mroy_1048.egg-info/requires.txt
x_mroy_1048.egg-info/top_level.txt