Metadata-Version: 1.0
Name: x-mroy-1048
Version: 0.2.0
Summary:  x-mroy
Home-page: https://github.com/Qingluan/.git
Author: Qing luan
Author-email: darkhackdevil@gmail.com
License: MIT
Platform: UNKNOWN
